LICENSE
MANIFEST.in
a2x-test.py
setup.py
a2x/__init__.py
a2x/a2s.py
a2x/fields.py
a2x.egg-info/PKG-INFO
a2x.egg-info/SOURCES.txt
a2x.egg-info/dependency_links.txt
a2x.egg-info/pbr.json
a2x.egg-info/top_level.txt